cinergia/__init__.py
cinergia/client.py
cinergia-1.0.1.dist-info/DESCRIPTION.rst
cinergia-1.0.1.dist-info/METADATA
cinergia-1.0.1.dist-info/RECORD
cinergia-1.0.1.dist-info/WHEEL
cinergia-1.0.1.dist-info/metadata.json
cinergia-1.0.1.dist-info/top_level.txt
