Metadata-Version: 2.0
Name: cinergia
Version: 1.0.1
Summary: Library for communication with cinergia electronic loads
Home-page: http://github.com/cedricboudinet/python-cinergia
Author: Cedric Boudinet
Author-email: boudinpg@gmail.com
License: LGPL-3.0
Platform: UNKNOWN
Classifier: Development Status :: 4 - Beta
Classifier: Environment :: Console
Classifier: Intended Audience :: Developers
Classifier: License :: OSI Approved :: GNU Lesser General Public License v3 (LGPLv3)
Classifier: Operating System :: Microsoft :: Windows
Classifier: Operating System :: POSIX
Classifier: Programming Language :: Python
Classifier: Topic :: Scientific/Engineering
Requires-Dist: pymodbus
